<?xml version="1.0" encoding="UTF-8"?>
<exemplars-best-file_ND_5><IL_HL_Weights>
<i1>-0.10294309993425|-0.0024775023922195|-0.088276530970704|0.021914216942173|-0.057058043343513|-0.069747725324835|-0.029095012807537|0.030369456034874|0.17433471650928|-0.015296698122093|-0.069994207435827|0.088725184535219|0.015742389674049|-0.0066341077458195|-0.040831961002394|-0.087849105256214|-0.11712347849088|-0.091568828573778|-0.07568257472341|-0.06336165298634|</i1>
<i2>0.10899272339718|-0.025862981418037|-0.10235071422385|-0.12223744392604|-0.17705902976053|-0.099150458049197|0.0074190830229879|-0.028883900224471|0.16854186420858|-0.034602185535089|-0.070857913999868|0.038305010939301|-0.037066605033567|-0.038156242718222|-0.089520672983878|0.046794779283758|0.019654092251379|0.017004253299734|-0.0009807735692914|-0.02584956580194|</i2>
<i3>0.072680175561165|0.029549284611697|0.064795980431958|0.046393060287626|-0.068164196386807|-0.13909851110453|-0.0068587913473989|-0.098478270701074|0.18811810990392|-0.12335474617392|0.051688548849576|0.084250178671524|0.071666115572377|0.091685978621464|0.019276696174191|-0.01447883453607|-0.082984252511691|-0.10134389340199|0.062899254056829|-0.091167774265965|</i3>
<i4>0.19785125277526|-0.087772673450215|0.046684015971259|-0.025627947782663|-0.31244165255892|-0.009630436117813|-0.036277458531252|-0.036385068079557|0.1959638016712|0.0011696171567973|0.074386812972409|-0.01382633846717|-0.036677736959381|-0.060512904710985|0.059619171055458|0.056438799713335|-0.12925621987866|0.08539651672664|0.050760332576814|0.045146065198701|</i4>
<i5>-0.49955497989491|-0.018066965776658|-0.0060553615848749|-0.10962843534856|0.0051467387452173|-0.080528582889695|-0.077516220942066|-0.15387200946856|0.065476200413916|0.043549178727908|-0.016194430011395|0.12716335553948|0.026678013112213|-0.050012409865264|-0.18602714783054|-0.34674666711097|-0.01183335873444|-0.2415702300932|0.027089480027509|-0.28560865593819|</i5>
<i6>-0.068143080264838|0.072416871230912|-0.074887315751979|0.036748356459065|-0.0040383812640914|-0.13255447751653|-0.016724854762978|-0.17552086730432|0.22802064047048|0.038743960646943|-0.079403185532435|0.082131949683558|0.03107253381247|0.006605215692299|-0.064632758579585|-0.060658700363785|0.029762336438822|-0.034786714696022|-0.077469758588055|0.0044083738741624|</i6>
<i7>0.062740750801791|-0.020486165764966|-0.01054661468257|0.079470397691902|0.036703434569396|0.0051287419460456|0.043335504881382|0.00026911431135938|0.042718941820536|0.060434657531525|0.063613731172208|-0.15289101896898|-0.0048836492740365|0.034448347603659|-0.012743588511415|-0.075173947836161|0.07228375383661|0.16645446337835|0.010036784831528|-0.024767769149514|</i7>
<i8>0.0011654109969302|-0.024962210797145|0.072953656951937|-0.084443467667502|0.07218316272938|-0.060772237490226|0.088782424197889|-0.12409100405551|0.0044352662961162|0.0376142445361|-0.070163240948037|0.23409674446244|0.063304982015565|-0.028019095522718|-0.0062472920997554|0.071402215801304|-0.044427244454738|0.062005421379771|-0.0003140086847242|-0.10255306371184|</i8>
<i9>0.014818763531796|-0.062244673221361|0.071750863590801|-0.02347674208261|0.1111017064102|-0.076613137816216|0.060620884793856|-0.15644726536451|-0.1136060235131|0.075730629086544|-0.045121066760982|0.27286881704893|-0.052534263894231|-0.03871027782791|-0.081677276248564|0.040028857780568|0.11602797568417|0.0099111593150327|0.0028238105898301|0.036401228441185|</i9>
<i10>-0.31715918257535|-0.065731614285973|-0.33605781655756|-0.14850583557663|0.019954707761961|0.0198597720036|-0.08602566488508|-0.10117375123982|-0.046706516422209|-0.21449920458188|-0.09570684623632|0.038019864608515|0.049835547109485|0.027810982856204|-0.089648470187713|-0.36842820493567|-0.0055010624221967|-0.10559353275403|0.015964017768043|-0.2042119568732|</i10>
<i11>-0.0063097122809325|-0.056448927343306|0.019692233617463|0.014642797270759|0.017479660456464|-0.087963024857367|0.0018536699905948|0.095408367803211|0.070279152707987|0.10208346358766|-0.059110277659882|-0.055077417189052|-0.065986231226549|0.10000329368928|-0.0048780865766039|0.12677205989077|-0.0870937790024|0.042232289881406|-0.080363574157714|-0.010986922899136|</i11>
<i12>0.086620705854518|-0.090351331076673|0.079358987221013|-0.041471553339959|-0.054700156788721|0.053538393178268|-0.017827425776532|-0.05897988926517|0.026363661633443|0.021242453117741|-0.0095839228270617|-0.0069022408619874|0.019472350155697|0.027072045664793|0.070953418385246|0.06613230288108|0.024899341071176|0.044784387667122|0.013189507433203|-0.024686409346837|</i12>
<i13>-0.12374896748457|0.043127777815605|-0.112830431409|0.073161197550944|-0.072365828228426|-0.12061628220048|0.012724181176695|0.025609536232974|-0.023089705705813|-0.10898912131166|-0.0077976269932331|-0.18369916376232|0.055950027943607|0.01816325475799|-0.020015162849454|0.13286693664699|0.05533215979494|-0.056096313438973|0.00062743386151716|-0.0093240254813669|</i13>
<i14>0.57246802413333|0.013474506920112|0.22489472726888|-0.13240033637402|0.0076496809482563|0.065858701009906|-0.032719290274778|0.015259591197064|-0.058757374407574|-0.063286901175399|-0.074369270348072|0.061459307561204|0.061022720131073|0.05018284717643|0.010334551779188|-0.036080757554458|-0.092725844449317|-0.12766021830923|0.041216758828841|0.37272214186143|</i14>
<i15>0.16639751554046|-0.029418728883403|0.14763309662618|0.27127173977379|-0.36877633348241|-0.30926090155495|-0.053674414982295|-0.0089174763063493|0.1202008278478|0.036069373789922|0.076988866909288|0.026632445271156|0.056480716539972|0.052311580413581|0.07499495306453|0.37640617713759|-0.15698677017568|0.045270988945317|0.079857236846176|0.31755255612121|</i15>
<i16>-0.055107039097971|0.097355401461516|-0.60014869885904|0.079760741060478|0.097256249900917|-0.012992697816159|-0.089189842050995|0.0099159893937913|-0.039629041009842|-0.053047002095328|0.079784998869097|0.021348540928174|0.039123203595626|-0.08118197427773|-0.13520288299067|-0.1217078505095|0.0068764586186071|0.062841851160325|-0.013301660892868|-0.51201603429303|</i16>
<i17>-0.11590896477302|-0.00021033385733165|0.063226221742511|-0.31092352125112|-0.049469478842388|0.089395377996512|-0.081397078300371|0.11563107487467|0.19805488640014|0.027051753388324|0.056895225502919|-0.046905819934594|-0.023193626439934|0.057819853723342|-0.10251190606178|-0.14288518516307|0.033990799231784|0.048198155958556|-0.069269309984545|-0.051967971843671|</i17>
<i18>-0.056321344351253|0.04589635898161|0.11464292466079|0.042552579072149|-0.11132066276915|-0.058091645173025|-0.085645567947972|0.065351245333227|-0.018831447041832|0.091865164093836|0.075620996775977|-0.0051257127301841|0.040790415408695|0.072159492489414|-0.093941507113785|-0.06630842407897|0.026927904425306|0.048133293926778|-0.054315940453163|-0.077354664856981|</i18>
<i19>-0.22407069605108|0.029933996977972|-0.20411749277199|-0.16738601241201|0.1315174228507|0.33381769453584|0.041826513382157|0.0013380419901353|-0.25769149845134|-0.066442913854525|0.026722680313577|0.28956238611426|-0.063488961520514|0.010031163819656|-0.17493973505783|-0.039209264195165|-0.0070632351133228|-0.095556865512952|-0.091811375617705|-0.010094486181936|</i19>
<i20>0.11848909109768|-0.058332167125633|0.17418031077727|-0.051751270640925|-0.025797680012231|0.038780743906489|0.076739731620517|-0.054291319543838|-0.024632098022204|0.12274164801006|0.076803444709092|0.025465215322425|0.042904878179992|0.02007847243931|-0.11586113349484|0.37498014535994|-0.11708725196249|0.1017234788641|-0.04398503022022|0.029674709269441|</i20>
<i21>0.16366790574966|0.08132070890035|-0.087191329572635|-0.080385225219231|0.03851902655719|0.10486318795418|-0.077022861248247|-0.039954921670963|0.087610208602602|-0.055703012846529|-0.079154371436986|-0.071132923344411|0.083684279321885|-0.084426728038155|-0.072964311815872|0.053366061467199|-0.036786765925601|0.094166306399326|-0.013936343333924|0.061965986928072|</i21>
<i22>0.011565291125818|0.03063850445259|-0.051372093689785|0.028417520010936|-0.31487568609779|0.019151828674298|-0.046012387666095|-0.0038797060628471|0.03796126546622|0.10833861278312|-0.013563084388914|-0.65504610926712|-0.0073762035728515|-0.038887835601993|0.11485134899727|0.036705829167449|-0.31140204786064|0.1787236761713|-0.093718199079922|0.015445280055062|</i22>
<i23>-0.042444574875593|0.043775547680502|-0.20531376576043|-0.057192865855595|-0.043664576563727|0.092946233840571|-0.10684623021583|-0.066497236570674|-0.1082736299561|0.020667319686792|0.063020605218406|-0.028751417661496|0.058931094608393|0.031594809326956|0.073884766058881|0.43940229550927|0.024482736876956|0.057215866310599|-0.070821587278936|0.047580715988216|</i23>
<i24>0.060306661616311|0.055689986894821|-0.071410801859126|0.38013042567901|0.04029221142555|-0.12314396093824|-0.07507767369899|0.24639033589976|0.5096471913481|0.027419121166096|-0.037645638417786|-0.50653350649995|0.07568088175807|0.035963353327935|-0.04011300640395|0.44062938780582|-0.16678233165009|0.2933078195764|-0.042632164286051|0.032707837411778|</i24>
<i25>-0.28043701149894|0.016253366836917|0.064806690230743|-0.27246187165397|0.54886964158882|0.06891140444507|-0.086981837366196|0.038126214870268|-0.084551729736106|0.023005013689564|0.043531433533759|0.14585751481442|-0.046102284991719|-0.013056124314803|-0.12655139167761|-0.12173665966598|-0.064726301992916|-0.055819420357154|-0.04696289179193|0.073556314381601|</i25>
<i26>-0.3514603381402|-0.041992945394597|0.074263351064019|-0.69509715041209|0.21577002397067|0.1840951643193|0.07604495239725|0.065564422829717|-0.12563279305092|0.011120222792301|0.020354452180757|0.05213768379562|0.092804021352102|-0.011491264957014|0.10822320363736|0.045282401809522|-0.046638898123552|-0.028350477528244|0.011239001275772|0.10059167119528|</i26>
<i27>0.1042245053569|-0.012938738397581|0.024776906506611|0.02531428343338|-0.18125296335644|-0.11661028326828|-0.012536271512678|-0.0893277435492|0.068467758033841|-0.043726604000286|-0.085830107943495|-0.087635926327518|-0.018984891781198|-0.081691304535176|0.21749960499796|0.062693741906682|-0.030245512334558|-0.0035707708998824|0.036964208636682|0.22427591529675|</i27>
<i28>-0.065597885447144|0.030622277397176|-0.058552886693855|-0.0800023565396|0.23583859699374|-0.21180373161401|0.080058104005009|-0.14263735763819|-0.44125470886219|-0.013127821393792|-0.075102673691695|0.368291915347|0.0010762792216408|-0.022037111045417|0.059050172973382|-0.2352752642664|-0.044519550327751|-0.24130499610605|-0.04935235064262|-0.074410037062281|</i28>
<i29>0.19273611955759|0.012958608695537|0.078522146995476|0.29154374544277|-0.22031848999794|-0.26619708085942|0.083150953555865|-0.04193457578062|0.015423059090043|0.063861926346024|-0.026762968078211|0.044896175416917|0.025817288359263|0.041217969074083|0.148539342692|0.091981422054543|-0.21265667781794|0.029804016951943|0.041701028741899|0.07695197609244|</i29>
<i30>-0.072163104400822|0.0068137922042953|-0.086640877761508|-0.13077013815679|0.13344806161805|0.23717431390635|0.029129854688428|-0.029738586562513|-0.044899122310702|-0.094191353736535|-0.086754908928389|0.13876380051651|-0.085165679889694|-0.036929741766436|-0.051489675964531|-0.043858682729773|-0.060860218866424|-0.095216302594511|-0.089767304509995|0.011983428070652|</i30>
<i31>-0.13592135909561|-0.057688020843061|0.027569732671152|-0.20164314455864|0.12269948840684|0.25245024859456|-0.076820496371881|0.031524621609143|-0.13163988342465|0.075486432404616|-0.020862516229298|0.26654238301707|0.070990183665958|-0.0097255529550666|0.026470253289825|-0.22869082335735|-0.099392318411257|-0.0079708321435073|-0.089699405811032|0.020291227559841|</i31>
<i32>-0.10013356212528|-0.083849151180276|-0.054414102350553|0.19552579346336|0.031862652641785|-0.017749885099573|-0.0013483606588174|-0.1737258408416|-0.061785072773505|0.10054223741829|0.028267736990222|0.20016955666734|-0.018902731014526|-0.023756951163756|0.081426953296656|0.32594889891578|0.03965248552181|0.2852276810765|-0.085691976585439|-0.0030155530875045|</i32>
<i33>-0.053938188217058|-0.0097570532562286|-0.13462637143227|-0.13089387324331|-0.094746346557485|0.15719931918491|-0.031321974211141|-0.18882149751019|-0.01237470595753|0.078189512970984|0.073334439580453|0.047168894545244|-0.011157851409567|0.050463689320929|-0.041096713287363|0.5984975580364|0.13748264802152|0.33115786207834|-0.015624069310362|-0.16174202068726|</i33>
<i34>-0.24137379178641|0.0018911822172914|-0.057404284976644|-0.36596441522768|0.064503573834041|0.31829633984375|0.020137644087442|-0.14567275170048|-0.34722048138944|-0.044159010055549|-0.045400911747108|0.0089868263061119|0.06101970224876|-0.037513702482658|-0.060776104343001|-0.34269561423481|0.07882292023864|-0.16200039139202|0.038969576273364|-0.14628353116906|</i34>
<i35>0.075818910738967|0.077232176422731|0.045373208438952|0.63161004765063|-0.12057676649763|0.27015785446403|0.060019405463384|0.01377728490115|0.1437600670812|0.12892519945109|0.015254498250919|-0.033976191424403|0.038563122945654|-0.052320337369637|-0.020178834029974|0.098199071777075|0.10470570221049|-0.079671480016213|0.04394098076678|0.0015999198530528|</i35>
<i36>-0.11800816083782|0.051653764833763|0.019107269713229|0.29887207883942|0.1064958069473|-0.020824084549678|0.0043154043784451|-0.019965981871532|-0.28166211619179|0.0038797232289098|0.075120685975235|-0.14965624211165|0.040733867051922|0.033988405644143|0.062744537346178|-0.15429460197344|-0.097673840667716|-0.058023981096777|0.073932228843502|-0.02293623999253|</i36>
<i37>-0.013113692424733|0.026920051457455|-0.028068585501404|-0.14341785695865|-0.013683802675057|-0.11329073882272|0.090731920652458|-0.10805748630403|-0.22061819676698|-0.02048749390182|-0.070184488479963|-0.28766706656858|-0.10560944155455|-0.030433750597384|0.071912343403225|-0.32315240394613|-0.055686502891884|-0.13145178062832|-0.081612387679436|0.013068085895961|</i37>
<i38>0.016118219379052|-0.0313879579327|0.040370668948375|0.45605094251151|-0.077036641681178|0.15067359239805|-0.093298654246054|-0.20883222369976|-0.016281313192962|0.033209962842249|0.05706772065648|-0.10601471744566|-0.0740571146866|0.011969475229224|0.075441004970105|-0.062356549471064|0.3494555451071|0.074133572474505|-0.041753803469374|0.028448352113352|</i38>
<i39>-0.02106612584999|0.063970033407692|0.057336603634636|0.3329953592142|0.10122521632426|0.063123462906847|0.072697352338885|-0.0080131105970242|0.26684666742176|0.016701640105406|-0.039595273462115|0.043272248053201|-0.026170193264715|-0.063862253443052|-0.13505185772|-0.03690548636154|0.28212026617464|0.063889347911071|-0.091225084220662|-0.06094964725158|</i39>
<i40>0.029999060287674|0.061122364086044|-0.11879087025027|-0.20607560324199|0.096972826309174|0.02980211606431|-0.10647326255636|0.044950661594263|-0.051253482960722|-0.18411685173253|0.072941953924571|0.1150337861955|-0.0091600055511782|-0.10170488209122|-0.054677062140693|-0.02789432529|0.18465777103585|-0.058862969751427|-0.10545642189413|0.067984051043544|</i40>
<i41>-0.069648902709839|0.025584196491454|-0.010459911724623|0.064243843100247|0.028927012184646|-0.049044675735446|-0.044373067086065|0.040201214784008|-0.075606191998446|-0.04373945180971|0.019767262469059|0.10600227598169|0.092909577344083|0.0487497473713|-0.07930390884606|-0.015868060648261|0.087821186875048|0.040169845569126|0.042098380285507|0.01515980098904|</i41>
<i42>-0.16027210109995|0.071248008364726|-0.070848016273597|-0.18604897428708|0.016980626023316|-0.036474517888752|-0.0058082264627901|-0.013121993415531|-0.19029141834209|-0.069281017466868|-0.012674564818119|-0.22544095703113|0.033609072211217|0.034962561302307|-0.06124701189309|-0.15796410792294|0.022462553625222|-0.037625163040794|0.060893325030547|-0.1638143098117|</i42>
<i43>0.13083826260355|0.057281768397533|-0.026984774148132|0.019333997594641|-0.069937717417662|-0.082394307106557|-0.012317345645057|0.15638732308089|0.10522861778541|-0.095706046551998|-0.05113203064126|-0.42961078696542|0.016365490307882|0.077204981631232|-0.017339304014686|-0.11603191130178|-0.02441764729866|-0.087504591341783|-0.017747180975563|0.090847514538912|</i43>
<i44>0.14486216673592|-0.094167796268669|0.15557277822908|-0.02085550849573|0.064966230130952|0.032590258636832|-0.053265560387394|0.111704881244|-0.026223047807281|-0.0530342534806|0.037658512875925|-0.0063408488514875|-0.0132582194291|-0.046060089773479|0.062119231459076|-0.020569990048637|-0.022457773675065|0.062192756276055|0.064049268288897|0.12852316973941|</i44>
<i45>-0.22764579627435|-0.041773965379901|-0.12308800252916|-0.1650275060494|0.22384402082878|0.28222541774489|0.071947850743121|0.065096281519084|-0.25591270150889|-0.12264606353073|0.011682781733021|-0.024292979602447|0.11366369997684|-0.019950616443346|0.017195208287247|-0.32526795592308|-0.017199464135791|-0.011346467186029|-0.017036342111912|-0.20088059811577|</i45>
<i46>-0.26097049049366|0.012684128723386|-0.21591304048667|-0.076548186965616|0.00020691292375582|-0.14840536590388|-0.066195759060211|-0.16188279153445|-0.082055783145447|0.007300761318043|-0.073799089545349|-0.05480691519604|0.029727386199663|0.036804664194539|0.12044986011893|0.57943959931117|0.022497195117226|-0.019671269616382|0.069198441725043|-0.23783816012705|</i46>
<i47>-0.22221696240712|0.031393681902314|-0.50496842927134|-0.093705856075747|-0.10601335749702|0.091980971953303|0.011848454931893|-0.069769875169834|-0.034195032649432|-0.009537504393564|-0.021713233408642|-0.16096323973514|-0.060302008679215|-0.061837260666471|-0.26243632800661|-0.18809018943165|0.28852882745645|-0.043762116111843|-0.10467714113506|-0.3137234355971|</i47>
<i48>-0.64405235448132|0.060760288274555|-0.40723569170431|-0.054292535216779|0.039063670274654|-0.077314041433266|0.0028021699215347|0.029907327862003|0.13213418312885|0.18205354573272|0.078809540758712|-0.23233377143494|0.010193987430176|0.035183920244018|-0.0084970256414418|0.27943286590011|0.13957771455938|0.22148506482945|0.048099663540721|-0.3133064265584|</i48>
<i49>-0.13158507637712|-0.072878587297935|-0.049362275246162|-0.18983644117221|0.073190308834972|-0.016721490516031|0.043750608415732|0.0092283054661953|0.27864129917496|0.07023081479585|0.053019672970991|-0.014552940489781|-0.019792691145394|-0.0073828982375007|-0.24383233071881|-0.42787398781314|-0.075769693863065|0.15736059944558|0.049631317722218|-0.30180159956599|</i49>
<i50>-0.14146870513053|-0.084110652470352|0.046528367473386|-0.27956548531866|-0.019370672194072|0.052753858022359|0.061361047818032|0.0064284098801344|0.12248983289694|0.03112553719655|-0.039469318158674|0.0033174527105704|0.07478739588974|-0.082766249407391|-0.11604914646567|-0.11376556455568|-0.05689499612773|0.096048128717445|-0.037490988926443|-0.030436755051848|</i50>
<i51>-0.2650971231141|-0.084223938815975|0.0010451214844911|-0.45240877203923|0.082640542871017|-0.059140790064225|-0.06476108975541|-0.042317228544634|-0.17898965055521|-0.0075334887084657|0.06491488204917|0.34011780636204|0.12705995099406|-0.0022182974922717|-0.23304202128108|-0.33469135204823|-0.052827329384936|-0.10924470634745|-0.043420841295083|-0.26281549501651|</i51>
<i52>0.17868086254302|0.041601662496249|0.023772941682838|0.53920809498991|-0.15837075600188|-0.20183325986985|0.072743329059948|0.053565384546027|0.18205134955092|0.099690206799138|-0.074646523291636|0.21753039457123|-0.024258654832034|-0.079319783930452|0.28902968875084|0.16761895936215|0.10403264359676|-0.019417321065275|0.0098875303780871|0.2878972606377|</i52>
<i53>0.32353378346072|0.072271011731129|-0.24220664893528|-0.099842388884686|0.041772001740578|0.18799650202939|0.052694595466344|0.11026612317074|-0.085257207367055|0.074619455972716|-0.033827459943513|-0.17618486895239|-0.031563700162072|-0.036500706192551|-0.67054870508753|0.12334500383654|0.016094257053023|-0.11745684176357|0.03784179101543|0.016405444505716|</i53>
<i54>0.015443197886474|-0.11936301028933|0.059348324861962|-0.26974250736935|0.15868175444703|0.2860230495538|0.06615336253623|-0.066538851070912|-0.20974879644087|0.050082456459197|0.046159966224054|0.067105873358008|-0.026463170549808|0.032959109905748|0.038686898052548|-0.23345972548687|-0.19843850280097|-0.12986867790276|-0.024960224355504|-0.12232574932474|</i54>
<i55>-0.3087726531693|0.047181467255905|-0.28780070290985|0.057253359036502|-0.037068072573237|-0.077996484272054|0.015643252428582|-0.07408457050183|-0.39594918760608|-0.12878098760033|-0.075173758820097|-0.046780065648865|-0.061674988547912|-0.12860616772207|-0.091922082229073|-0.086339186903038|0.068272388420866|-0.086418829737381|-0.028347670520195|-0.19856238088023|</i55>
<i56>0.2159153734722|-0.024937754657842|0.11970084465671|0.068615177225202|-0.10090034811987|0.12183535666453|-0.10480180309522|0.038836586387139|-0.27255712632344|-0.2167175518677|-0.01611665500364|-0.071322287078796|0.018731607662038|-0.030297319091988|-0.044255851994971|-0.35563192849484|0.14831383415315|-0.39209014098042|-0.019368908086457|0.11727051150181|</i56>
<i57>-0.099426073976496|-0.019493619158674|0.047134514012523|-0.046720493645909|-0.095706102461203|-0.23832851154015|-0.07525590224813|0.17233981156473|-0.1365317513204|0.088407872168489|-0.07804088625416|-0.27023372542566|-0.12830140443848|0.013446778154205|-0.051523881746168|-0.097564549554154|-0.19065046038529|0.065566568706175|-0.037235305292067|0.13176912223907|</i57>
<i58>-0.25021942990078|0.039346084183616|-0.058451387253972|-0.41770812309646|-0.15900590630169|-0.16592043147888|0.035661250351999|-0.044159583736484|0.14846386031534|-0.16915252213373|-0.055587120835023|-0.076367290096013|-0.041541308491016|-0.12450825997071|-0.13743792898565|-0.25775293886402|-0.057531158705946|0.12102918333075|0.035263131143769|-0.030578062921275|</i58>
<i59>-0.069672969643925|-0.13962260664468|-0.023236255034262|-0.13776510187766|-0.184374397226|-0.46259390132952|0.036023176524492|-0.034923348116697|0.016219009631161|0.036088221980572|-0.050250437982816|-0.25319216829446|-0.13984302883055|-0.012634894694543|0.0026921722814787|-0.031510093538779|-0.2139216382493|0.031638430804813|0.013426954288784|-0.071600534859446|</i59>
<i60>-0.25751196646501|-0.077585455760039|0.075187756410458|-0.52051627983937|-0.04358564086863|0.059701033588642|-0.13950269810526|-0.21704648915204|-0.63697624234326|-0.32099350318885|-0.16137881302902|0.085226428572988|-0.041589824334292|0.012528368509831|-0.14421617964203|-0.41830859457426|-0.099445039051652|-0.32455628515844|-0.054414402262887|-0.024761902508973|</i60>
<i61>0.034459354352219|0.021818089638731|-0.067975228278651|0.051077565769759|-0.25398451352008|-0.38742771565114|0.022917927886418|-0.18439426462297|-0.14429534703895|-0.031305277534798|-0.02386894845719|-0.042108186370394|-0.011715160988325|-0.10750328511915|0.037366051255492|-0.056796782601509|-0.016025773965138|-0.072386798193981|-0.12275281552612|0.066597550049252|</i61>
<i62>0.19107453989047|-0.10652818416911|0.097313854912237|-0.28964588326851|-0.10072210149588|0.033545652640236|-0.098571604947543|-0.16775388907489|-0.037339829398772|0.067793465031529|0.0022485112536839|-0.22201461510746|-0.011297737942194|-0.062862881538151|0.048845464672917|0.19472019301295|0.020427623987873|-0.11077393016201|-0.042580550832714|0.042313871192801|</i62>
<i63>-0.051337009115386|-0.13702112301459|-0.0016209409460695|-0.25210430692682|0.1563815258093|0.040037940789029|-0.076371172878012|-0.26890929126328|-0.30717123386723|-0.27848515978741|-0.16672948176097|-0.022288481595872|-0.022203994934312|0.019184939932384|-0.099509748665646|-0.20143608782363|-0.094705429085698|-0.31796783463942|-0.11405910688331|0.10026825296304|</i63>
<i64>-0.20178156648028|-0.013177074839086|-0.28876804615051|0.012687948112086|-0.16420920931265|0.13903384230273|0.020971081952181|0.0035684500801903|-0.032589374458561|-0.13069907009331|-0.075042286945268|0.013774090114864|0.023186160706485|-0.14136320205505|-0.045766995860592|0.046152843762706|0.14195194089456|0.044543387093536|-0.022018925278012|-0.22347701351346|</i64>
<i65>0.077219355782405|0.048892193340529|0.12330128225495|0.15096143755343|-0.11670319163124|0.17977534596892|-0.11138887884253|-0.10061107458183|-0.13629382302454|0.01947146495385|-0.09575004888212|-0.036994501506296|-0.074411709423173|0.0020581031760874|0.037585265554293|0.23256106144913|0.27841410282515|-0.036176453804|-0.043684209021886|-0.056427634668059|</i65>
<i66>0.036164681647754|-0.09686581254586|-0.081955709554558|-0.14668421953099|0.033029628733419|-0.094021436493154|-0.056215283205104|0.056605134435476|-0.12900361353549|-0.085252691367377|0.029490423958288|-0.030439630631037|-0.010566204780478|0.0040876440579381|0.056749691208684|-0.27382603219222|-0.26352561953392|-0.0023836306796435|0.0077382729007603|0.025829614353035|</i66>
<i67>-0.097667976694437|-0.13060595079931|-0.031740644580672|-0.28670907245121|0.073232689609192|0.023636691513677|-0.04374952976026|-0.10001270813587|-0.093970277992345|0.047554836119052|-0.050285620258216|-0.029556248901198|-0.0071574980951126|0.026072116961709|-0.12713556579662|-0.053109605020411|0.032401301873458|-0.11517995112903|-0.065626673286779|-0.18983440972157|</i67>
<i68>-0.092867071342726|-0.068813596156644|-0.15633811216888|-0.23192925529435|0.10889185385708|0.029555196930812|-0.03458425607871|-0.29271709646594|-0.14171252973322|-0.017165371044581|-0.021992166027754|-0.075577869419565|-0.10520695624899|-0.091338166161691|-0.13546966176649|0.089840416586031|-0.11637408834119|-0.13821157008795|-0.11077158145347|-0.13165921401696|</i68>
<i69>0.027751888360461|-0.055343861939939|-0.088913219300298|-0.29933038853329|-0.1571644081903|-0.1498200273393|-0.050585715138122|-0.31094820636474|-0.23472832953881|-0.16228983013762|-0.10994849916591|-0.074423375337708|-0.12650075973492|-0.18573714736447|-0.018931585518039|0.016508849355437|0.00065115493453367|-0.14249196934209|0.016713914837984|-0.052859534808486|</i69>
<i70>0.0028225686888559|0.040342087148242|-0.10801746181222|-0.10455310629779|-0.071037603542628|0.0066445380265018|-0.14528537192819|-0.22804388027179|-0.27668502403018|-0.23066853709979|-0.16919511284631|-0.14238745410603|-0.068687734108248|-0.041233405157738|-0.079571420499401|-0.045221340080478|-0.098564475274629|-0.094555112486297|-0.11992081797259|-0.13014226657082|</i70>
<i71>0.14612512281724|-0.080083406218506|0.099948357925118|0.18681171400578|0.13454180754064|0.01724990673255|0.045365486411394|-0.15449141415821|0.14707093541942|-0.018997970044063|-0.13981100472439|-0.17919467542412|-0.048684689486253|-0.036730601364935|-0.046927616281673|0.0077677469103336|-0.23157475528613|-0.057044332535594|0.0021332357746989|0.14466043867634|</i71>
<i72>0.23015713877721|0.0029884327802682|-0.089202823897123|0.17323814113625|0.13883884969721|0.14094448083808|-0.083653979333944|-0.23232047209573|0.16935545989072|0.0027755640168098|0.0030979914440925|-0.011001152437134|-0.0095463570490537|-0.084854680599524|0.079450499379331|0.22684470771988|-0.1491564144129|0.16604034764498|-0.061347555847666|0.12025857958674|</i72>
<i73>-0.049758044613101|-0.054457775009297|-0.23095856626351|0.079730938984543|-0.30225270081676|-0.088496590912725|-0.086800802858468|0.032598737307235|0.30717639237387|-0.071956554881144|-0.11775239979146|0.17473503948793|-0.13067586828422|0.058067709391326|-0.095534870866893|-0.04603716938774|0.076480390878964|0.035785252232636|0.059007444829954|-0.048021815603291|</i73>
<i74>0.024740454713859|-0.081300489324536|-0.018054154285734|0.11435270384626|-0.19366839251665|-0.11801634184889|-0.12744784087554|0.22048953234366|0.067360585980132|-0.0048350414932465|-0.0283891024504|0.16202645246837|-0.049006244482781|-0.088593428949385|0.00064500360852753|-0.18386373425498|-0.041418674789477|0.1138463378033|-0.11844518940538|-0.064886787705359|</i74>
<i75>0.022322745381458|-0.13273895806143|-0.035217641280325|0.0042767224060663|0.16258712635794|0.017028232287995|-0.078353638506838|0.070410750331769|-0.18681393684195|0.12064583202554|-0.022268689837386|-0.23894030735669|-0.086245952246574|-0.02876934764333|0.044967086697598|0.045887107551441|-0.42169897480646|0.051146873389267|0.07447980827127|-0.041579220622861|</i75>
<i76>-0.18837483740865|-0.013614912279725|-0.046097946650537|-0.43662572516909|0.054121688561521|0.066122422592848|-0.11614582387566|-0.13749758933109|-0.29660168830727|-0.11996130363276|-0.065674065743101|0.12288781248464|-0.003914211328505|-0.095837011905196|-0.08734696417463|-0.1691007680913|0.022381173857158|-0.074095085382535|-0.077241824512003|-0.15560628077545|</i76>
<i77>0.2358468759148|-0.15888872090415|-0.081924749816251|0.28773070236317|-0.048569422300205|-0.31886893725217|0.065422545703997|-0.014962768115694|0.28561341509859|0.067160088171818|-0.079469555919776|-0.43992279037472|-0.067624680896367|-0.050287174044323|-0.019029317551614|0.18216706502701|-0.1346637738725|0.02464168529069|-0.024390410287734|0.1955710311101|</i77>
<i78>0.071642613188444|-0.21370892442069|-0.13738954563591|0.26853303662534|-0.29011474222873|-0.39087407946996|-0.054596467676209|0.046514532212724|0.22984622797774|0.064356997124677|-0.11478567738771|-0.46431790146469|-0.0052043018369299|-0.11695950575316|-0.087595500148964|0.13616875603944|-0.31722517984714|-0.0094580887761453|-0.080198663567786|-0.029492108624091|</i78>
<i79>-0.44944180090945|-0.044051630683135|-0.42098176773888|-0.0584931105697|-0.0060534441756861|0.12130121362696|-0.083793005464524|-0.077134803949601|-0.17860191804154|-0.18293977039107|-0.10035414321996|0.060439660247142|-0.049538401912438|0.0049626262230003|-0.21819696554633|-0.31402205969553|0.0677380641881|-0.074521726289965|-0.025825084818981|-0.16405454957885|</i79>
<i80>-0.2104687456224|-0.069078032551503|-0.24589658364811|-0.043509118902579|0.18550827737129|0.13266239748827|-0.015970225686983|-0.25756074247901|-0.17497677840279|-0.31002217526296|-0.15664182063548|0.19377577503994|-0.096979219142576|-0.093676796982662|-0.12657208697687|-0.27882444765165|-0.090656339034773|-0.26744745077133|-0.10987375288239|0.015046969755813|</i80>
<i81>-0.046223373057222|-0.14039834712997|0.011920201292783|0.017061043842054|0.18512798997361|-0.034717490598705|-0.11801838102427|-0.1679219488566|0.10499749147874|-0.13974711317561|0.022081392537421|0.13618121166646|-0.078066062744457|-0.043666610252556|0.052653389505956|0.10520392159754|-0.039753715101488|0.03273803797604|-0.082806107404976|-0.12654119421952|</i81>
<iT>0.20745115782357|0.17185493531784|0.05238695202312|0.317200873155|0.35248637989362|0.41002209838751|0.18835790062313|0.019288522587411|-0.0099799442366133|0.022403462928884|0.044303177171538|0.17988457359918|0.14960296545645|0.099868864780569|0.24872272785723|0.25511937123853|0.19556647812306|0.13756695542496|0.19083851959942|0.26041766444333|</iT>
</IL_HL_Weights>
<HL_OL_Weights>
<j82>-1.0659399339929|-0.22444933526502|-0.25888576828873|-0.26796346888385|0.27759765249764|-0.2022533497346|</j82>
<j83>0.22278106564517|-0.16430987635422|-0.11327976478735|-0.099087670818065|0.22442388258934|-0.086460522974108|</j83>
<j84>-0.98311855884648|-0.11707557549478|-0.15888408295491|-0.16821537944161|0.15951855491208|-0.16289835907883|</j84>
<j85>-1.1206121928524|-0.17540231202876|-0.088080667340277|-0.19233883509498|0.1376359894964|-0.15657624014907|</j85>
<j86>0.74488068271495|-0.2748339462655|-0.30017605689506|-0.27452496000517|0.2557171164171|-0.32240271614405|</j86>
<j87>0.93018342910197|-0.086329875298443|-0.11019784572817|-0.12611661073963|0.16443486245106|-0.12826264244046|</j87>
<j88>-0.031054088669168|-0.13716214292499|-0.13260437141452|-0.18814439104098|0.18048088939951|-0.066481157273432|</j88>
<j89>-1.1464067201878|-0.11144663611179|-0.13426465877238|-0.11285265844403|-0.0061731948293623|-0.024463984021553|</j89>
<j90>-1.1635951302733|-0.13458421712598|-0.21922786685661|-0.091754989601022|0.17882946997606|-0.13316256803825|</j90>
<j91>-0.72437063078528|-0.14180193984576|-0.10603081984734|-0.18019359363976|0.19153267649405|-0.13303073171976|</j91>
<j92>-0.21709671837637|-0.15881570812842|-0.060693437500101|-0.12474080639477|0.094561762802264|-0.11177599896271|</j92>
<j93>1.3352620415006|-0.10578317446639|-0.25049564901035|-0.23890808155233|0.090680819142507|-0.18065619705854|</j93>
<j94>0.032827421264193|-0.20894935309345|-0.29489581603673|-0.32940321570053|0.20345875848678|-0.35527762043187|</j94>
<j95>-0.078191465451448|-0.1734865513315|-0.1766913391207|-0.077689324046972|0.13511080107841|-0.20050087883262|</j95>
<j96>-0.9024270533711|-0.072080736465055|-0.24134182254071|-0.21013014999521|0.20069499532662|-0.19059901784021|</j96>
<j97>-1.3804258059955|-0.19509075995031|-0.18219801473215|-0.13447389680192|0.18852830150059|-0.28600701516043|</j97>
<j98>1.0035337416965|-0.19620676308771|-0.31300272561537|-0.25340115557713|0.33256096168621|-0.23478630477342|</j98>
<j99>-0.75032820927361|-0.090470827297407|-0.010291038361893|-0.082496277194637|0.06723008663507|-0.033840861799057|</j99>
<j100>-0.069523588164307|-0.20459523424222|-0.15055514824619|-0.23560700546018|0.11007989871438|-0.16806775353852|</j100>
<j101>-0.20780800640167|-0.15380488492999|-0.085411110480196|-0.11499082470842|0.1403712287122|-0.1955426172409|</j101>
<jT>-0.063864380779845|1.0653048784032|1.0593691972851|1.0532340245961|-1.0571329140491|1.05118507158|</jT>
</HL_OL_Weights>
</exemplars-best-file_ND_5>